tellopy/__init__.py
tellopy/_internal/__init__.py
tellopy/_internal/crc.py
tellopy/_internal/dispatcher.py
tellopy/_internal/error.py
tellopy/_internal/event.py
tellopy/_internal/logger.py
tellopy/_internal/protocol.py
tellopy/_internal/state.py
tellopy/_internal/tello.py
tellopy/_internal/utils.py
tellopy/_internal/video_stream.py
tellopy/examples/__init__.py
tellopy/examples/joystick_and_video.py
tellopy/examples/simple_takeoff.py
tellopy/examples/video_effect.py
tellopy-0.5.0.dist-info/LICENSE.txt
tellopy-0.5.0.dist-info/METADATA
tellopy-0.5.0.dist-info/RECORD
tellopy-0.5.0.dist-info/WHEEL
tellopy-0.5.0.dist-info/top_level.txt
