Metadata-Version: 2.1
Name: tellopy
Version: 0.5.0
Summary: DJI Tello drone controller
Home-page: https://github.com/hanyazou/TelloPy
Author: Hanyazou
Author-email: hanyazou@gmail.com
License: UNKNOWN
Project-URL: Source, https://github.com/hanyazou/TelloPy
Project-URL: Bug Reports, https://github.com/hanyazou/TelloPy/issues
Project-URL: Say Thanks!, https://twitter.com/hanyazou
Keywords: sample development robotics drone
Platform: UNKNOWN
Classifier: Development Status :: 3 - Alpha
Classifier: Intended Audience :: Developers
Classifier: Topic :: Software Development :: Libraries
Classifier: License :: OSI Approved :: Apache Software License
Classifier: Programming Language :: Python :: 2.7
Classifier: Programming Language :: Python :: 3.5
Classifier: Programming Language :: Python :: 3.6
Requires-Python: >=2.7, !=3.0.*, !=3.1.*, !=3.2.*, !=3.3.*, !=3.4.*, <4
